lback/__init__.py
lback/main.py
lback/admin/__init__.py
lback/admin/admin.py
lback/admin/auth_views.py
lback/admin/generic.py
lback/admin/registry.py
lback/admin/urls.py
lback/admin/views.py
lback/api/__init__.py
lback/api/docs.py
lback/api/generics.py
lback/api/mixins.py
lback/api/serializer.py
lback/api/view.py
lback/auth/__init__.py
lback/auth/adminauth.py
lback/auth/jwt_auth.py
lback/auth/oauth.py
lback/auth/password_hashing.py
lback/auth/permissions.py
lback/auth/session_auth.py
lback/auth_app/__init__.py
lback/auth_app/auth_forms.py
lback/auth_app/auth_views.py
lback/auth_app/urls.py
lback/auth_app/web_auth_views.py
lback/commands/__init__.py
lback/commands/admin.py
lback/commands/app.py
lback/commands/db_seed.py
lback/commands/migration.py
lback/commands/project.py
lback/commands/runner.py
lback/conf/alembic_template/alembic.ini.template
lback/conf/alembic_template/env.py.template
lback/conf/alembic_template/script.py.mako.template
lback/conf/app_templates/__init__.py.template
lback/conf/app_templates/admin.py.template
lback/conf/app_templates/models.py.template
lback/conf/app_templates/serializers.py.template
lback/conf/app_templates/urls.py.template
lback/conf/app_templates/views.py.template
lback/conf/project_templates/Lback_Logo.png
lback/conf/project_templates/__init__.py.template
lback/conf/project_templates/env.template
lback/conf/project_templates/manage.py.template
lback/conf/project_templates/settings.py.template
lback/conf/project_templates/tailwind.min.css
lback/conf/project_templates/urls.py.template
lback/conf/project_templates/wsgi.py.template
lback/core/__init__.py
lback/core/app_controller.py
lback/core/base_middleware.py
lback/core/cache.py
lback/core/config.py
lback/core/config_manager.py
lback/core/dispatcher_instance.py
lback/core/error_handler.py
lback/core/exceptions.py
lback/core/logging_setup.py
lback/core/middleware_loader.py
lback/core/middleware_manager.py
lback/core/response.py
lback/core/router.py
lback/core/server.py
lback_framework-1.0.3.dist-info/licenses/LICENSE
lback_framework-1.0.3.dist-info/METADATA
lback_framework-1.0.3.dist-info/WHEEL
lback_framework-1.0.3.dist-info/entry_points.txt
lback_framework-1.0.3.dist-info/top_level.txt
lback_framework-1.0.3.dist-info/RECORD
