Metadata-Version: 2.4
Name: lback_framework
Version: 1.0.3
Summary: A modern and powerful Python web framework.
Home-page: https://github.com/hemaabokila/lback_framework
Author: Ibrahem Abokila
Author-email: ibrahemabokila@gmail.com
License: MIT
Classifier: Development Status :: 3 - Alpha
Classifier: Intended Audience :: Developers
Classifier: License :: OSI Approved :: MIT License
Classifier: Programming Language :: Python :: 3
Classifier: Programming Language :: Python :: 3.8
Classifier: Programming Language :: Python :: 3.9
Classifier: Programming Language :: Python :: 3.10
Classifier: Programming Language :: Python :: 3.11
Classifier: Programming Language :: Python :: 3.12
Classifier: Operating System :: OS Independent
Classifier: Topic :: Internet :: WWW/HTTP :: WSGI :: Application
Classifier: Topic :: Software Development :: Libraries :: Application Frameworks
Requires-Python: >=3.8
License-File: LICENSE
Requires-Dist: alembic~=1.15.2
Requires-Dist: attrs~=25.3.0
Requires-Dist: bcrypt~=4.3.0
Requires-Dist: boltons~=21.0.0
Requires-Dist: bracex~=2.5.post1
Requires-Dist: certifi~=2025.1.31
Requires-Dist: cffi~=1.17.1
Requires-Dist: charset-normalizer~=3.4.1
Requires-Dist: click~=8.1.8
Requires-Dist: click-option-group~=0.5.7
Requires-Dist: colorama~=0.4.6
Requires-Dist: cryptography~=44.0.2
Requires-Dist: defusedxml~=0.7.1
Requires-Dist: Deprecated~=1.2.18
Requires-Dist: dill~=0.4.0
Requires-Dist: exceptiongroup~=1.2.2
Requires-Dist: face~=24.0.0
Requires-Dist: glom~=22.1.0
Requires-Dist: googleapis-common-protos~=1.70.0
Requires-Dist: greenlet~=3.1.1
Requires-Dist: idna~=3.10
Requires-Dist: importlib_metadata~=7.1.0
Requires-Dist: Jinja2~=3.1.6
Requires-Dist: jsonschema~=4.23.0
Requires-Dist: jsonschema-specifications~=2025.4.1
Requires-Dist: jwt==1.3.1
Requires-Dist: Mako~=1.3.10
Requires-Dist: markdown-it-py~=3.0.0
Requires-Dist: MarkupSafe~=3.0.2
Requires-Dist: mdurl~=0.1.2
Requires-Dist: opentelemetry-api~=1.25.0
Requires-Dist: opentelemetry-exporter-otlp-proto-common~=1.25.0
Requires-Dist: opentelemetry-exporter-otlp-proto-http~=1.25.0
Requires-Dist: opentelemetry-instrumentation~=0.46b0
Requires-Dist: opentelemetry-instrumentation-requests~=0.46b0
Requires-Dist: opentelemetry-proto~=1.25.0
Requires-Dist: opentelemetry-sdk~=1.25.0
Requires-Dist: opentelemetry-semantic-conventions~=0.46b0
Requires-Dist: opentelemetry-util-http~=0.46b0
Requires-Dist: packaging~=25.0
Requires-Dist: pbr~=6.1.1
Requires-Dist: platformdirs~=4.3.7
Requires-Dist: protobuf~=4.25.7
Requires-Dist: pycparser~=2.22
Requires-Dist: Pygments~=2.19.1
Requires-Dist: PyJWT~=2.10.1
Requires-Dist: python-dotenv~=1.1.0
Requires-Dist: python-magic~=0.4.14; platform_system != "Windows"
Requires-Dist: python-magic-bin~=0.4.14; platform_system == "Windows"
Requires-Dist: python-multipart~=0.0.20
Requires-Dist: python-slugify~=8.0.4
Requires-Dist: PyYAML~=6.0.2
Requires-Dist: referencing~=0.36.2
Requires-Dist: requests~=2.32.3
Requires-Dist: rich~=13.5.3
Requires-Dist: rpds-py~=0.24.0
Requires-Dist: ruamel.yaml~=0.18.10
Requires-Dist: ruamel.yaml.clib~=0.2.12
Requires-Dist: setuptools~=80.3.0
Requires-Dist: slugify~=0.0.1
Requires-Dist: SQLAlchemy~=2.0.40
Requires-Dist: stevedore~=5.4.1
Requires-Dist: text-unidecode~=1.3
Requires-Dist: tomli~=2.0.2
Requires-Dist: tomlkit~=0.13.2
Requires-Dist: typing_extensions~=4.13.1
Requires-Dist: urllib3~=2.4.0
Requires-Dist: watchdog~=6.0.0
Requires-Dist: wcmatch~=8.5.2
Requires-Dist: websockets~=15.0.1
Requires-Dist: Werkzeug~=3.1.3
Requires-Dist: wrapt~=1.17.2
Requires-Dist: zipp~=3.21.0
Provides-Extra: testing
Requires-Dist: bandit~=1.8.3; extra == "testing"
Requires-Dist: coverage~=7.8.0; extra == "testing"
Requires-Dist: isort~=6.0.1; extra == "testing"
Requires-Dist: pytest~=8.3.5; extra == "testing"
Requires-Dist: mypy~=1.15.0; extra == "testing"
Requires-Dist: pylint~=3.3.6; extra == "testing"
Provides-Extra: dev
Requires-Dist: bandit~=1.8.3; extra == "dev"
Requires-Dist: coverage~=7.8.0; extra == "dev"
Requires-Dist: isort~=6.0.1; extra == "dev"
Requires-Dist: pytest~=8.3.5; extra == "dev"
Requires-Dist: mypy~=1.15.0; extra == "dev"
Requires-Dist: pylint~=3.3.6; extra == "dev"
Requires-Dist: flake8; extra == "dev"
Requires-Dist: build; extra == "dev"
Requires-Dist: twine; extra == "dev"
Dynamic: author
Dynamic: author-email
Dynamic: classifier
Dynamic: description
Dynamic: description-content-type
Dynamic: home-page
Dynamic: license
Dynamic: license-file
Dynamic: provides-extra
Dynamic: requires-dist
Dynamic: requires-python
Dynamic: summary
